src/__init__.py
src/main.py
src/handlers/__init__.py
src/handlers/ldap_connect.py
src/handlers/profile.py
src/helpers/__init__.py
src/helpers/filetime_to_date.py
src/helpers/user.py
src/modules/__init__.py
src/modules/enum/__init__.py
src/modules/enum/administrators.py
src/modules/enum/all_computers.py
src/modules/enum/all_users.py
src/modules/enum/disabled_accounts.py
src/modules/enum/domain_controllers.py
src/modules/enum/fqdn.py
src/modules/enum/kerberoasting.py
src/modules/enum/laps.py
src/modules/enum/maq_acc_quota.py
src/modules/enum/obsolete.py
src/modules/enum/pass_not_req.py
src/modules/enum/pass_pol.py
src/modules/enum/trusted_delegation.py
src/modules/user/__init__.py
src/modules/user/whoami.py
src/ui/__init__.py
src/ui/banner.py
breads_ad-1.1.2.dist-info/LICENSE
breads_ad-1.1.2.dist-info/METADATA
breads_ad-1.1.2.dist-info/WHEEL
breads_ad-1.1.2.dist-info/entry_points.txt
breads_ad-1.1.2.dist-info/top_level.txt
breads_ad-1.1.2.dist-info/RECORD
