Metadata-Version: 2.1
Name: breads-ad
Version: 1.1.2
Summary: Breaking Active Directory Security (BREADS) is a tool design to attack Active Directory environments
Home-page: https://github.com/inferigang/breads
Author: oppsec
Author-email: opps3c@gmail.com
License: UNKNOWN
Platform: UNKNOWN
Classifier: Programming Language :: Python :: 3
Classifier: License :: OSI Approved :: MIT License
Classifier: Operating System :: OS Independent
Requires-Python: >=3.10.12
License-File: LICENSE
Requires-Dist: python-ldap (>=3.4.4)
Requires-Dist: requests (>=2.31.0)
Requires-Dist: rich (>=13.5.3)
